{"data": {"00001": [{"person_id": [-1], "pose_keypoints_2d": [105.41, 64.135, 0.812601, 98.3535, 95.9737, 0.551112, 54.7176, 90.0961, 0.536687, 0, 0, 0, 0, 0, 0, 129.007, 101.852, 0.109616, 0, 0, 0, 0, 0, 0, 0, 0, 0, 0, 0, 0, 0, 0, 0, 0, 0, 0, 0, 0, 0, 0, 0, 0, 0, 0, 0, 93.6091, 53.5225, 0.815789, 117.156, 54.7412, 0.852908, 78.2466, 58.2627, 0.788447, 128.993, 60.6276, 0.510021, 0, 0, 0, 0, 0, 0, 0, 0, 0, 0, 0, 0, 0, 0, 0, 0, 0, 0], "face_keypoints_2d": [], "hand_left_keypoints_2d": [0, 0, 0, 0, 0, 0, 0, 0, 0, 0, 0, 0, 0, 0, 0, 0, 0, 0, 0, 0, 0, 0, 0, 0, 0, 0, 0, 0, 0, 0, 0, 0, 0, 0, 0, 0, 0, 0, 0, 0, 0, 0, 0, 0, 0, 0, 0, 0, 0, 0, 0, 0, 0, 0, 0, 0, 0, 0, 0, 0, 0, 0, 0], "hand_right_keypoints_2d": [0, 0, 0, 0, 0, 0, 0, 0, 0, 0, 0, 0, 0, 0, 0, 0, 0, 0, 0, 0, 0, 0, 0, 0, 0, 0, 0, 0, 0, 0, 0, 0, 0, 0, 0, 0, 0, 0, 0, 0, 0, 0, 0, 0, 0, 0, 0, 0, 0, 0, 0, 0, 0, 0, 0, 0, 0, 0, 0, 0, 0, 0, 0], "pose_keypoints_3d": [], "face_keypoints_3d": [], "hand_left_keypoints_3d": [], "hand_right_keypoints_3d": []}], "00002": [{"person_id": [-1], "pose_keypoints_2d": [105.413, 64.1251, 0.804278, 98.3352, 95.9806, 0.562069, 53.5489, 91.2375, 0.531238, 0, 0, 0, 0, 0, 0, 129.008, 100.707, 0.111569, 0, 0, 0, 0, 0, 0, 0, 0, 0, 0, 0, 0, 0, 0, 0, 0, 0, 0, 0, 0, 0, 0, 0, 0, 0, 0, 0, 93.6042, 52.4031, 0.8142, 117.167, 54.7395, 0.846882, 78.2484, 58.2433, 0.781115, 128.993, 60.6392, 0.468733, 0, 0, 0, 0, 0, 0, 0, 0, 0, 0, 0, 0, 0, 0, 0, 0, 0, 0], "face_keypoints_2d": [], "hand_left_keypoints_2d": [0, 0, 0, 0, 0, 0, 0, 0, 0, 0, 0, 0, 0, 0, 0, 0, 0, 0, 0, 0, 0, 0, 0, 0, 0, 0, 0, 0, 0, 0, 0, 0, 0, 0, 0, 0, 0, 0, 0, 0, 0, 0, 0, 0, 0, 0, 0, 0, 0, 0, 0, 0, 0, 0, 0, 0, 0, 0, 0, 0, 0, 0, 0], "hand_right_keypoints_2d": [0, 0, 0, 0, 0, 0, 0, 0, 0, 0, 0, 0, 0, 0, 0, 0, 0, 0, 0, 0, 0, 0, 0, 0, 0, 0, 0, 0, 0, 0, 0, 0, 0, 0, 0, 0, 0, 0, 0, 0, 0, 0, 0, 0, 0, 0, 0, 0, 0, 0, 0, 0, 0, 0, 0, 0, 0, 0, 0, 0, 0, 0, 0], "pose_keypoints_3d": [], "face_keypoints_3d": [], "hand_left_keypoints_3d": [], "hand_right_keypoints_3d": []}], "00003": [{"person_id": [-1], "pose_keypoints_2d": [106.529, 63.0106, 0.785987, 98.3402, 97.1337, 0.480799, 52.3891, 92.4255, 0.455882, 0, 0, 0, 0, 0, 0, 129.008, 101.863, 0.0701967, 0, 0, 0, 0, 0, 0, 0, 0, 0, 0, 0, 0, 0, 0, 0, 0, 0, 0, 0, 0, 0, 0, 0, 0, 0, 0, 0, 93.603, 52.4017, 0.791665, 117.177, 54.7143, 0.833331, 78.2519, 58.2579, 0.763068, 128.994, 60.6351, 0.445115, 0, 0, 0, 0, 0, 0, 0, 0, 0, 0, 0, 0, 0, 0, 0, 0, 0, 0], "face_keypoints_2d": [], "hand_left_keypoints_2d": [0, 0, 0, 0, 0, 0, 0, 0, 0, 0, 0, 0, 0, 0, 0, 0, 0, 0, 0, 0, 0, 0, 0, 0, 0, 0, 0, 0, 0, 0, 0, 0, 0, 0, 0, 0, 0, 0, 0, 0, 0, 0, 0, 0, 0, 0, 0, 0, 0, 0, 0, 0, 0, 0, 0, 0, 0, 0, 0, 0, 0, 0, 0], "hand_right_keypoints_2d": [0, 0, 0, 0, 0, 0, 0, 0, 0, 0, 0, 0, 0, 0, 0, 0, 0, 0, 0, 0, 0, 0, 0, 0, 0, 0, 0, 0, 0, 0, 0, 0, 0, 0, 0, 0, 0, 0, 0, 0, 0, 0, 0, 0, 0, 0, 0, 0, 0, 0, 0, 0, 0, 0, 0, 0, 0, 0, 0, 0, 0, 0, 0], "pose_keypoints_3d": [], "face_keypoints_3d": [], "hand_left_keypoints_3d": [], "hand_right_keypoints_3d": []}], "00004": [{"person_id": [-1], "pose_keypoints_2d": [105.412, 63.012, 0.814386, 98.3263, 97.1285, 0.566608, 53.5188, 92.4439, 0.533448, 0, 0, 0, 0, 0, 0, 129.007, 100.675, 0.109811, 0, 0, 0, 0, 0, 0, 0, 0, 0, 0, 0, 0, 0, 0, 0, 0, 0, 0, 0, 0, 0, 0, 0, 0, 0, 0, 0, 93.6129, 52.4153, 0.824738, 117.16, 54.7328, 0.855587, 78.2458, 58.2638, 0.790121, 128.993, 60.6556, 0.495825, 0, 0, 0, 0, 0, 0, 0, 0, 0, 0, 0, 0, 0, 0, 0, 0, 0, 0], "face_keypoints_2d": [], "hand_left_keypoints_2d": [0, 0, 0, 0, 0, 0, 0, 0, 0, 0, 0, 0, 0, 0, 0, 0, 0, 0, 0, 0, 0, 0, 0, 0, 0, 0, 0, 0, 0, 0, 0, 0, 0, 0, 0, 0, 0, 0, 0, 0, 0, 0, 0, 0, 0, 0, 0, 0, 0, 0, 0, 0, 0, 0, 0, 0, 0, 0, 0, 0, 0, 0, 0], "hand_right_keypoints_2d": [0, 0, 0, 0, 0, 0, 0, 0, 0, 0, 0, 0, 0, 0, 0, 0, 0, 0, 0, 0, 0, 0, 0, 0, 0, 0, 0, 0, 0, 0, 0, 0, 0, 0, 0, 0, 0, 0, 0, 0, 0, 0, 0, 0, 0, 0, 0, 0, 0, 0, 0, 0, 0, 0, 0, 0, 0, 0, 0, 0, 0, 0, 0], "pose_keypoints_3d": [], "face_keypoints_3d": [], "hand_left_keypoints_3d": [], "hand_right_keypoints_3d": []}], "00005": [{"person_id": [-1], "pose_keypoints_2d": [106.524, 64.1531, 0.803341, 97.143, 97.1403, 0.5484, 51.1664, 93.6029, 0.488457, 0, 0, 0, 0, 0, 0, 129.008, 100.68, 0.115067, 0, 0, 0, 0, 0, 0, 0, 0, 0, 0, 0, 0, 0, 0, 0, 0, 0, 0, 0, 0, 0, 0, 0, 0, 0, 0, 0, 93.6183, 52.4024, 0.82098, 117.164, 55.8821, 0.849133, 77.1267, 57.087, 0.772388, 128.993, 60.6383, 0.447535, 0, 0, 0, 0, 0, 0, 0, 0, 0, 0, 0, 0, 0, 0, 0, 0, 0, 0], "face_keypoints_2d": [], "hand_left_keypoints_2d": [0, 0, 0, 0, 0, 0, 0, 0, 0, 0, 0, 0, 0, 0, 0, 0, 0, 0, 0, 0, 0, 0, 0, 0, 0, 0, 0, 0, 0, 0, 0, 0, 0, 0, 0, 0, 0, 0, 0, 0, 0, 0, 0, 0, 0, 0, 0, 0, 0, 0, 0, 0, 0, 0, 0, 0, 0, 0, 0, 0, 0, 0, 0], "hand_right_keypoints_2d": [0, 0, 0, 0, 0, 0, 0, 0, 0, 0, 0, 0, 0, 0, 0, 0, 0, 0, 0, 0, 0, 0, 0, 0, 0, 0, 0, 0, 0, 0, 0, 0, 0, 0, 0, 0, 0, 0, 0, 0, 0, 0, 0, 0, 0, 0, 0, 0, 0, 0, 0, 0, 0, 0, 0, 0, 0, 0, 0, 0, 0, 0, 0], "pose_keypoints_3d": [], "face_keypoints_3d": [], "hand_left_keypoints_3d": [], "hand_right_keypoints_3d": []}], "00006": [{"person_id": [-1], "pose_keypoints_2d": [105.393, 64.1362, 0.774502, 97.1176, 97.1303, 0.442967, 50.0166, 94.7802, 0.405423, 0, 0, 0, 0, 0, 0, 129.008, 100.672, 0.116867, 0, 0, 0, 0, 0, 0, 0, 0, 0, 0, 0, 0, 0, 0, 0, 0, 0, 0, 0, 0, 0, 0, 0, 0, 0, 0, 0, 93.5872, 52.4039, 0.786794, 117.153, 55.8998, 0.820142, 77.1098, 59.3965, 0.751189, 128.992, 61.7429, 0.39647, 0, 0, 0, 0, 0, 0, 0, 0, 0, 0, 0, 0, 0, 0, 0, 0, 0, 0], "face_keypoints_2d": [], "hand_left_keypoints_2d": [0, 0, 0, 0, 0, 0, 0, 0, 0, 0, 0, 0, 0, 0, 0, 0, 0, 0, 0, 0, 0, 0, 0, 0, 0, 0, 0, 0, 0, 0, 0, 0, 0, 0, 0, 0, 0, 0, 0, 0, 0, 0, 0, 0, 0, 0, 0, 0, 0, 0, 0, 0, 0, 0, 0, 0, 0, 0, 0, 0, 0, 0, 0], "hand_right_keypoints_2d": [0, 0, 0, 0, 0, 0, 0, 0, 0, 0, 0, 0, 0, 0, 0, 0, 0, 0, 0, 0, 0, 0, 0, 0, 0, 0, 0, 0, 0, 0, 0, 0, 0, 0, 0, 0, 0, 0, 0, 0, 0, 0, 0, 0, 0, 0, 0, 0, 0, 0, 0, 0, 0, 0, 0, 0, 0, 0, 0, 0, 0, 0, 0], "pose_keypoints_3d": [], "face_keypoints_3d": [], "hand_left_keypoints_3d": [], "hand_right_keypoints_3d": []}], "00007": [{"person_id": [-1], "pose_keypoints_2d": [105.381, 64.1655, 0.798223, 98.2919, 95.9476, 0.573175, 52.3962, 91.2729, 0.564613, 0, 0, 0, 0, 0, 0, 129.008, 99.4995, 0.139069, 0, 0, 0, 0, 0, 0, 0, 0, 0, 0, 0, 0, 0, 0, 0, 0, 0, 0, 0, 0, 0, 0, 0, 0, 0, 0, 0, 93.6007, 53.5142, 0.81948, 117.148, 57.0515, 0.844504, 77.1188, 58.2501, 0.780932, 128.993, 61.7575, 0.457433, 0, 0, 0, 0, 0, 0, 0, 0, 0, 0, 0, 0, 0, 0, 0, 0, 0, 0], "face_keypoints_2d": [], "hand_left_keypoints_2d": [0, 0, 0, 0, 0, 0, 0, 0, 0, 0, 0, 0, 0, 0, 0, 0, 0, 0, 0, 0, 0, 0, 0, 0, 0, 0, 0, 0, 0, 0, 0, 0, 0, 0, 0, 0, 0, 0, 0, 0, 0, 0, 0, 0, 0, 0, 0, 0, 0, 0, 0, 0, 0, 0, 0, 0, 0, 0, 0, 0, 0, 0, 0], "hand_right_keypoints_2d": [0, 0, 0, 0, 0, 0, 0, 0, 0, 0, 0, 0, 0, 0, 0, 0, 0, 0, 0, 0, 0, 0, 0, 0, 0, 0, 0, 0, 0, 0, 0, 0, 0, 0, 0, 0, 0, 0, 0, 0, 0, 0, 0, 0, 0, 0, 0, 0, 0, 0, 0, 0, 0, 0, 0, 0, 0, 0, 0, 0, 0, 0, 0], "pose_keypoints_3d": [], "face_keypoints_3d": [], "hand_left_keypoints_3d": [], "hand_right_keypoints_3d": []}], "00008": [{"person_id": [-1], "pose_keypoints_2d": [106.534, 62.9999, 0.766232, 97.1432, 98.2739, 0.338352, 51.1704, 93.6118, 0.305904, 0, 0, 0, 0, 0, 0, 129.007, 106.551, 0.0754247, 0, 0, 0, 0, 0, 0, 0, 0, 0, 0, 0, 0, 0, 0, 0, 0, 0, 0, 0, 0, 0, 0, 0, 0, 0, 0, 0, 94.7623, 52.3944, 0.766837, 117.182, 54.7425, 0.809334, 78.2828, 58.253, 0.711672, 128.993, 61.7364, 0.376828, 0, 0, 0, 0, 0, 0, 0, 0, 0, 0, 0, 0, 0, 0, 0, 0, 0, 0], "face_keypoints_2d": [], "hand_left_keypoints_2d": [0, 0, 0, 0, 0, 0, 0, 0, 0, 0, 0, 0, 0, 0, 0, 0, 0, 0, 0, 0, 0, 0, 0, 0, 0, 0, 0, 0, 0, 0, 0, 0, 0, 0, 0, 0, 0, 0, 0, 0, 0, 0, 0, 0, 0, 0, 0, 0, 0, 0, 0, 0, 0, 0, 0, 0, 0, 0, 0, 0, 0, 0, 0], "hand_right_keypoints_2d": [0, 0, 0, 0, 0, 0, 0, 0, 0, 0, 0, 0, 0, 0, 0, 0, 0, 0, 0, 0, 0, 0, 0, 0, 0, 0, 0, 0, 0, 0, 0, 0, 0, 0, 0, 0, 0, 0, 0, 0, 0, 0, 0, 0, 0, 0, 0, 0, 0, 0, 0, 0, 0, 0, 0, 0, 0, 0, 0, 0, 0, 0, 0], "pose_keypoints_3d": [], "face_keypoints_3d": [], "hand_left_keypoints_3d": [], "hand_right_keypoints_3d": []}], "00009": [{"person_id": [-1], "pose_keypoints_2d": [106.59, 63.011, 0.794475, 93.5964, 98.3251, 0.276264, 42.9514, 91.2576, 0.283152, 0, 0, 0, 0, 0, 0, 129.006, 108.955, 0.0887438, 0, 0, 0, 0, 0, 0, 0, 0, 0, 0, 0, 0, 0, 0, 0, 0, 0, 0, 0, 0, 0, 0, 0, 0, 0, 0, 0, 95.9379, 52.4073, 0.782352, 117.224, 55.8952, 0.824896, 78.2803, 58.2691, 0.698584, 128.996, 61.756, 0.415749, 0, 0, 0, 0, 0, 0, 0, 0, 0, 0, 0, 0, 0, 0, 0, 0, 0, 0], "face_keypoints_2d": [], "hand_left_keypoints_2d": [0, 0, 0, 0, 0, 0, 0, 0, 0, 0, 0, 0, 0, 0, 0, 0, 0, 0, 0, 0, 0, 0, 0, 0, 0, 0, 0, 0, 0, 0, 0, 0, 0, 0, 0, 0, 0, 0, 0, 0, 0, 0, 0, 0, 0, 0, 0, 0, 0, 0, 0, 0, 0, 0, 0, 0, 0, 0, 0, 0, 0, 0, 0], "hand_right_keypoints_2d": [0, 0, 0, 0, 0, 0, 0, 0, 0, 0, 0, 0, 0, 0, 0, 0, 0, 0, 0, 0, 0, 0, 0, 0, 0, 0, 0, 0, 0, 0, 0, 0, 0, 0, 0, 0, 0, 0, 0, 0, 0, 0, 0, 0, 0, 0, 0, 0, 0, 0, 0, 0, 0, 0, 0, 0, 0, 0, 0, 0, 0, 0, 0], "pose_keypoints_3d": [], "face_keypoints_3d": [], "hand_left_keypoints_3d": [], "hand_right_keypoints_3d": []}], "00010": [{"person_id": [-1], "pose_keypoints_2d": [107.703, 64.1235, 0.776614, 95.9718, 98.3359, 0.236857, 47.6282, 93.6135, 0.233677, 0, 0, 0, 0, 0, 0, 129.006, 110.116, 0.0745756, 0, 0, 0, 0, 0, 0, 0, 0, 0, 0, 0, 0, 0, 0, 0, 0, 0, 0, 0, 0, 0, 0, 0, 0, 0, 0, 0, 97.0951, 52.4013, 0.770425, 118.308, 55.9008, 0.80409, 79.4298, 57.0932, 0.696493, 128.996, 61.764, 0.409665, 0, 0, 0, 0, 0, 0, 0, 0, 0, 0, 0, 0, 0, 0, 0, 0, 0, 0], "face_keypoints_2d": [], "hand_left_keypoints_2d": [0, 0, 0, 0, 0, 0, 0, 0, 0, 0, 0, 0, 0, 0, 0, 0, 0, 0, 0, 0, 0, 0, 0, 0, 0, 0, 0, 0, 0, 0, 0, 0, 0, 0, 0, 0, 0, 0, 0, 0, 0, 0, 0, 0, 0, 0, 0, 0, 0, 0, 0, 0, 0, 0, 0, 0, 0, 0, 0, 0, 0, 0, 0], "hand_right_keypoints_2d": [0, 0, 0, 0, 0, 0, 0, 0, 0, 0, 0, 0, 0, 0, 0, 0, 0, 0, 0, 0, 0, 0, 0, 0, 0, 0, 0, 0, 0, 0, 0, 0, 0, 0, 0, 0, 0, 0, 0, 0, 0, 0, 0, 0, 0, 0, 0, 0, 0, 0, 0, 0, 0, 0, 0, 0, 0, 0, 0, 0, 0, 0, 0], "pose_keypoints_3d": [], "face_keypoints_3d": [], "hand_left_keypoints_3d": [], "hand_right_keypoints_3d": []}], "00011": [{"person_id": [-1], "pose_keypoints_2d": [107.729, 64.1355, 0.768875, 97.1406, 98.2975, 0.249614, 50.0079, 92.4158, 0.25418, 0, 0, 0, 0, 0, 0, 129.006, 108.97, 0.0754003, 0, 0, 0, 0, 0, 0, 0, 0, 0, 0, 0, 0, 0, 0, 0, 0, 0, 0, 0, 0, 0, 0, 0, 0, 0, 0, 0, 97.1132, 52.3967, 0.750029, 118.362, 57.0669, 0.784896, 79.4793, 59.4364, 0.722003, 128.999, 61.8292, 0.439224, 0, 0, 0, 0, 0, 0, 0, 0, 0, 0, 0, 0, 0, 0, 0, 0, 0, 0], "face_keypoints_2d": [], "hand_left_keypoints_2d": [0, 0, 0, 0, 0, 0, 0, 0, 0, 0, 0, 0, 0, 0, 0, 0, 0, 0, 0, 0, 0, 0, 0, 0, 0, 0, 0, 0, 0, 0, 0, 0, 0, 0, 0, 0, 0, 0, 0, 0, 0, 0, 0, 0, 0, 0, 0, 0, 0, 0, 0, 0, 0, 0, 0, 0, 0, 0, 0, 0, 0, 0, 0], "hand_right_keypoints_2d": [0, 0, 0, 0, 0, 0, 0, 0, 0, 0, 0, 0, 0, 0, 0, 0, 0, 0, 0, 0, 0, 0, 0, 0, 0, 0, 0, 0, 0, 0, 0, 0, 0, 0, 0, 0, 0, 0, 0, 0, 0, 0, 0, 0, 0, 0, 0, 0, 0, 0, 0, 0, 0, 0, 0, 0, 0, 0, 0, 0, 0, 0, 0], "pose_keypoints_3d": [], "face_keypoints_3d": [], "hand_left_keypoints_3d": [], "hand_right_keypoints_3d": []}], "00012": [{"person_id": [-1], "pose_keypoints_2d": [107.777, 64.15, 0.79257, 97.1609, 97.1473, 0.20237, 51.1561, 92.4159, 0.26865, 0, 0, 0, 0, 0, 0, 129.005, 108.936, 0.0572053, 0, 0, 0, 0, 0, 0, 0, 0, 0, 0, 0, 0, 0, 0, 0, 0, 0, 0, 0, 0, 0, 0, 0, 0, 0, 0, 0, 98.2682, 52.4046, 0.785539, 118.394, 58.2214, 0.786359, 79.5031, 59.4342, 0.739609, 129.002, 62.988, 0.403897, 0, 0, 0, 0, 0, 0, 0, 0, 0, 0, 0, 0, 0, 0, 0, 0, 0, 0], "face_keypoints_2d": [], "hand_left_keypoints_2d": [0, 0, 0, 0, 0, 0, 0, 0, 0, 0, 0, 0, 0, 0, 0, 0, 0, 0, 0, 0, 0, 0, 0, 0, 0, 0, 0, 0, 0, 0, 0, 0, 0, 0, 0, 0, 0, 0, 0, 0, 0, 0, 0, 0, 0, 0, 0, 0, 0, 0, 0, 0, 0, 0, 0, 0, 0, 0, 0, 0, 0, 0, 0], "hand_right_keypoints_2d": [0, 0, 0, 0, 0, 0, 0, 0, 0, 0, 0, 0, 0, 0, 0, 0, 0, 0, 0, 0, 0, 0, 0, 0, 0, 0, 0, 0, 0, 0, 0, 0, 0, 0, 0, 0, 0, 0, 0, 0, 0, 0, 0, 0, 0, 0, 0, 0, 0, 0, 0, 0, 0, 0, 0, 0, 0, 0, 0, 0, 0, 0, 0], "pose_keypoints_3d": [], "face_keypoints_3d": [], "hand_left_keypoints_3d": [], "hand_right_keypoints_3d": []}], "00013": [{"person_id": [-1], "pose_keypoints_2d": [108.921, 65.3244, 0.789982, 99.4757, 98.291, 0.412228, 51.2034, 94.8004, 0.442853, 0, 0, 0, 0, 0, 0, 0, 0, 0, 0, 0, 0, 0, 0, 0, 0, 0, 0, 0, 0, 0, 0, 0, 0, 0, 0, 0, 0, 0, 0, 0, 0, 0, 0, 0, 0, 98.3263, 53.5422, 0.778556, 119.525, 58.2212, 0.765446, 80.597, 59.3951, 0.773834, 129.004, 62.945, 0.417025, 0, 0, 0, 0, 0, 0, 0, 0, 0, 0, 0, 0, 0, 0, 0, 0, 0, 0], "face_keypoints_2d": [], "hand_left_keypoints_2d": [0, 0, 0, 0, 0, 0, 0, 0, 0, 0, 0, 0, 0, 0, 0, 0, 0, 0, 0, 0, 0, 0, 0, 0, 0, 0, 0, 0, 0, 0, 0, 0, 0, 0, 0, 0, 0, 0, 0, 0, 0, 0, 0, 0, 0, 0, 0, 0, 0, 0, 0, 0, 0, 0, 0, 0, 0, 0, 0, 0, 0, 0, 0], "hand_right_keypoints_2d": [0, 0, 0, 0, 0, 0, 0, 0, 0, 0, 0, 0, 0, 0, 0, 0, 0, 0, 0, 0, 0, 0, 0, 0, 0, 0, 0, 0, 0, 0, 0, 0, 0, 0, 0, 0, 0, 0, 0, 0, 0, 0, 0, 0, 0, 0, 0, 0, 0, 0, 0, 0, 0, 0, 0, 0, 0, 0, 0, 0, 0, 0, 0], "pose_keypoints_3d": [], "face_keypoints_3d": [], "hand_left_keypoints_3d": [], "hand_right_keypoints_3d": []}], "00014": [{"person_id": [-1], "pose_keypoints_2d": [108.949, 66.5057, 0.694418, 98.2876, 98.269, 0.178971, 51.1443, 94.7894, 0.249038, 0, 0, 0, 0, 0, 0, 0, 0, 0, 0, 0, 0, 0, 0, 0, 0, 0, 0, 0, 0, 0, 0, 0, 0, 0, 0, 0, 0, 0, 0, 0, 0, 0, 0, 0, 0, 98.3501, 53.5533, 0.658605, 119.568, 59.3845, 0.703119, 80.6188, 60.5602, 0.676723, 129.006, 64.1237, 0.338467, 0, 0, 0, 0, 0, 0, 0, 0, 0, 0, 0, 0, 0, 0, 0, 0, 0, 0], "face_keypoints_2d": [], "hand_left_keypoints_2d": [0, 0, 0, 0, 0, 0, 0, 0, 0, 0, 0, 0, 0, 0, 0, 0, 0, 0, 0, 0, 0, 0, 0, 0, 0, 0, 0, 0, 0, 0, 0, 0, 0, 0, 0, 0, 0, 0, 0, 0, 0, 0, 0, 0, 0, 0, 0, 0, 0, 0, 0, 0, 0, 0, 0, 0, 0, 0, 0, 0, 0, 0, 0], "hand_right_keypoints_2d": [0, 0, 0, 0, 0, 0, 0, 0, 0, 0, 0, 0, 0, 0, 0, 0, 0, 0, 0, 0, 0, 0, 0, 0, 0, 0, 0, 0, 0, 0, 0, 0, 0, 0, 0, 0, 0, 0, 0, 0, 0, 0, 0, 0, 0, 0, 0, 0, 0, 0, 0, 0, 0, 0, 0, 0, 0, 0, 0, 0, 0, 0, 0], "pose_keypoints_3d": [], "face_keypoints_3d": [], "hand_left_keypoints_3d": [], "hand_right_keypoints_3d": []}], "00015": [{"person_id": [-1], "pose_keypoints_2d": [108.935, 67.648, 0.689183, 98.3259, 98.2802, 0.215212, 51.1654, 95.9441, 0.276878, 0, 0, 0, 0, 0, 0, 0, 0, 0, 0, 0, 0, 0, 0, 0, 0, 0, 0, 0, 0, 0, 0, 0, 0, 0, 0, 0, 0, 0, 0, 0, 0, 0, 0, 0, 0, 98.3358, 53.5637, 0.656183, 119.551, 59.3995, 0.699969, 80.6319, 59.4343, 0.654856, 129.005, 64.1246, 0.332557, 0, 0, 0, 0, 0, 0, 0, 0, 0, 0, 0, 0, 0, 0, 0, 0, 0, 0], "face_keypoints_2d": [], "hand_left_keypoints_2d": [0, 0, 0, 0, 0, 0, 0, 0, 0, 0, 0, 0, 0, 0, 0, 0, 0, 0, 0, 0, 0, 0, 0, 0, 0, 0, 0, 0, 0, 0, 0, 0, 0, 0, 0, 0, 0, 0, 0, 0, 0, 0, 0, 0, 0, 0, 0, 0, 0, 0, 0, 0, 0, 0, 0, 0, 0, 0, 0, 0, 0, 0, 0], "hand_right_keypoints_2d": [0, 0, 0, 0, 0, 0, 0, 0, 0, 0, 0, 0, 0, 0, 0, 0, 0, 0, 0, 0, 0, 0, 0, 0, 0, 0, 0, 0, 0, 0, 0, 0, 0, 0, 0, 0, 0, 0, 0, 0, 0, 0, 0, 0, 0, 0, 0, 0, 0, 0, 0, 0, 0, 0, 0, 0, 0, 0, 0, 0, 0, 0, 0], "pose_keypoints_3d": [], "face_keypoints_3d": [], "hand_left_keypoints_3d": [], "hand_right_keypoints_3d": []}], "00016": [{"person_id": [-1], "pose_keypoints_2d": [108.912, 66.4985, 0.720517, 98.3551, 98.3084, 0.296635, 51.1745, 97.1086, 0.350137, 0, 0, 0, 0, 0, 0, 0, 0, 0, 0, 0, 0, 0, 0, 0, 0, 0, 0, 0, 0, 0, 0, 0, 0, 0, 0, 0, 0, 0, 0, 0, 0, 0, 0, 0, 0, 98.2889, 53.5604, 0.682742, 119.539, 58.2533, 0.701867, 79.5111, 60.535, 0.731964, 129.006, 62.9652, 0.345253, 0, 0, 0, 0, 0, 0, 0, 0, 0, 0, 0, 0, 0, 0, 0, 0, 0, 0], "face_keypoints_2d": [], "hand_left_keypoints_2d": [0, 0, 0, 0, 0, 0, 0, 0, 0, 0, 0, 0, 0, 0, 0, 0, 0, 0, 0, 0, 0, 0, 0, 0, 0, 0, 0, 0, 0, 0, 0, 0, 0, 0, 0, 0, 0, 0, 0, 0, 0, 0, 0, 0, 0, 0, 0, 0, 0, 0, 0, 0, 0, 0, 0, 0, 0, 0, 0, 0, 0, 0, 0], "hand_right_keypoints_2d": [0, 0, 0, 0, 0, 0, 0, 0, 0, 0, 0, 0, 0, 0, 0, 0, 0, 0, 0, 0, 0, 0, 0, 0, 0, 0, 0, 0, 0, 0, 0, 0, 0, 0, 0, 0, 0, 0, 0, 0, 0, 0, 0, 0, 0, 0, 0, 0, 0, 0, 0, 0, 0, 0, 0, 0, 0, 0, 0, 0, 0, 0, 0], "pose_keypoints_3d": [], "face_keypoints_3d": [], "hand_left_keypoints_3d": [], "hand_right_keypoints_3d": []}], "00017": [{"person_id": [-1], "pose_keypoints_2d": [107.799, 66.5017, 0.762308, 98.3494, 98.314, 0.357131, 51.185, 95.9763, 0.393279, 0, 0, 0, 0, 0, 0, 0, 0, 0, 0, 0, 0, 0, 0, 0, 0, 0, 0, 0, 0, 0, 0, 0, 0, 0, 0, 0, 0, 0, 0, 0, 0, 0, 0, 0, 0, 98.2652, 53.5556, 0.730919, 118.427, 58.2694, 0.756198, 79.5088, 59.4375, 0.773133, 129.005, 62.9755, 0.373982, 0, 0, 0, 0, 0, 0, 0, 0, 0, 0, 0, 0, 0, 0, 0, 0, 0, 0], "face_keypoints_2d": [], "hand_left_keypoints_2d": [0, 0, 0, 0, 0, 0, 0, 0, 0, 0, 0, 0, 0, 0, 0, 0, 0, 0, 0, 0, 0, 0, 0, 0, 0, 0, 0, 0, 0, 0, 0, 0, 0, 0, 0, 0, 0, 0, 0, 0, 0, 0, 0, 0, 0, 0, 0, 0, 0, 0, 0, 0, 0, 0, 0, 0, 0, 0, 0, 0, 0, 0, 0], "hand_right_keypoints_2d": [0, 0, 0, 0, 0, 0, 0, 0, 0, 0, 0, 0, 0, 0, 0, 0, 0, 0, 0, 0, 0, 0, 0, 0, 0, 0, 0, 0, 0, 0, 0, 0, 0, 0, 0, 0, 0, 0, 0, 0, 0, 0, 0, 0, 0, 0, 0, 0, 0, 0, 0, 0, 0, 0, 0, 0, 0, 0, 0, 0, 0, 0, 0], "pose_keypoints_3d": [], "face_keypoints_3d": [], "hand_left_keypoints_3d": [], "hand_right_keypoints_3d": []}], "00018": [{"person_id": [-1], "pose_keypoints_2d": [108.882, 66.4846, 0.739015, 98.3126, 98.3061, 0.320187, 51.1773, 94.8041, 0.372056, 0, 0, 0, 0, 0, 0, 0, 0, 0, 0, 0, 0, 0, 0, 0, 0, 0, 0, 0, 0, 0, 0, 0, 0, 0, 0, 0, 0, 0, 0, 0, 0, 0, 0, 0, 0, 98.2731, 53.537, 0.720263, 118.425, 58.2669, 0.744485, 79.493, 59.4194, 0.757587, 129.004, 62.987, 0.384627, 0, 0, 0, 0, 0, 0, 0, 0, 0, 0, 0, 0, 0, 0, 0, 0, 0, 0], "face_keypoints_2d": [], "hand_left_keypoints_2d": [0, 0, 0, 0, 0, 0, 0, 0, 0, 0, 0, 0, 0, 0, 0, 0, 0, 0, 0, 0, 0, 0, 0, 0, 0, 0, 0, 0, 0, 0, 0, 0, 0, 0, 0, 0, 0, 0, 0, 0, 0, 0, 0, 0, 0, 0, 0, 0, 0, 0, 0, 0, 0, 0, 0, 0, 0, 0, 0, 0, 0, 0, 0], "hand_right_keypoints_2d": [0, 0, 0, 0, 0, 0, 0, 0, 0, 0, 0, 0, 0, 0, 0, 0, 0, 0, 0, 0, 0, 0, 0, 0, 0, 0, 0, 0, 0, 0, 0, 0, 0, 0, 0, 0, 0, 0, 0, 0, 0, 0, 0, 0, 0, 0, 0, 0, 0, 0, 0, 0, 0, 0, 0, 0, 0, 0, 0, 0, 0, 0, 0], "pose_keypoints_3d": [], "face_keypoints_3d": [], "hand_left_keypoints_3d": [], "hand_right_keypoints_3d": []}], "00019": [{"person_id": [-1], "pose_keypoints_2d": [107.798, 66.5044, 0.764029, 98.3432, 98.2857, 0.389944, 51.196, 95.9394, 0.425918, 0, 0, 0, 0, 0, 0, 0, 0, 0, 0, 0, 0, 0, 0, 0, 0, 0, 0, 0, 0, 0, 0, 0, 0, 0, 0, 0, 0, 0, 0, 0, 0, 0, 0, 0, 0, 98.2678, 53.5511, 0.74733, 118.424, 59.3898, 0.762426, 79.5038, 59.4377, 0.781345, 129.005, 62.979, 0.354883, 0, 0, 0, 0, 0, 0, 0, 0, 0, 0, 0, 0, 0, 0, 0, 0, 0, 0], "face_keypoints_2d": [], "hand_left_keypoints_2d": [0, 0, 0, 0, 0, 0, 0, 0, 0, 0, 0, 0, 0, 0, 0, 0, 0, 0, 0, 0, 0, 0, 0, 0, 0, 0, 0, 0, 0, 0, 0, 0, 0, 0, 0, 0, 0, 0, 0, 0, 0, 0, 0, 0, 0, 0, 0, 0, 0, 0, 0, 0, 0, 0, 0, 0, 0, 0, 0, 0, 0, 0, 0], "hand_right_keypoints_2d": [0, 0, 0, 0, 0, 0, 0, 0, 0, 0, 0, 0, 0, 0, 0, 0, 0, 0, 0, 0, 0, 0, 0, 0, 0, 0, 0, 0, 0, 0, 0, 0, 0, 0, 0, 0, 0, 0, 0, 0, 0, 0, 0, 0, 0, 0, 0, 0, 0, 0, 0, 0, 0, 0, 0, 0, 0, 0, 0, 0, 0, 0, 0], "pose_keypoints_3d": [], "face_keypoints_3d": [], "hand_left_keypoints_3d": [], "hand_right_keypoints_3d": []}], "00020": [{"person_id": [-1], "pose_keypoints_2d": [108.877, 66.4873, 0.754667, 98.2751, 98.2861, 0.219179, 49.9951, 97.1105, 0.290698, 0, 0, 0, 0, 0, 0, 0, 0, 0, 0, 0, 0, 0, 0, 0, 0, 0, 0, 0, 0, 0, 0, 0, 0, 0, 0, 0, 0, 0, 0, 0, 0, 0, 0, 0, 0, 98.2826, 53.5426, 0.737803, 118.422, 59.3775, 0.75968, 79.4985, 59.4187, 0.764441, 129.003, 62.9722, 0.373474, 0, 0, 0, 0, 0, 0, 0, 0, 0, 0, 0, 0, 0, 0, 0, 0, 0, 0], "face_keypoints_2d": [], "hand_left_keypoints_2d": [0, 0, 0, 0, 0, 0, 0, 0, 0, 0, 0, 0, 0, 0, 0, 0, 0, 0, 0, 0, 0, 0, 0, 0, 0, 0, 0, 0, 0, 0, 0, 0, 0, 0, 0, 0, 0, 0, 0, 0, 0, 0, 0, 0, 0, 0, 0, 0, 0, 0, 0, 0, 0, 0, 0, 0, 0, 0, 0, 0, 0, 0, 0], "hand_right_keypoints_2d": [0, 0, 0, 0, 0, 0, 0, 0, 0, 0, 0, 0, 0, 0, 0, 0, 0, 0, 0, 0, 0, 0, 0, 0, 0, 0, 0, 0, 0, 0, 0, 0, 0, 0, 0, 0, 0, 0, 0, 0, 0, 0, 0, 0, 0, 0, 0, 0, 0, 0, 0, 0, 0, 0, 0, 0, 0, 0, 0, 0, 0, 0, 0], "pose_keypoints_3d": [], "face_keypoints_3d": [], "hand_left_keypoints_3d": [], "hand_right_keypoints_3d": []}], "00021": [{"person_id": [-1], "pose_keypoints_2d": [107.804, 66.5179, 0.754113, 98.348, 98.3337, 0.367885, 51.1589, 95.9714, 0.404738, 0, 0, 0, 0, 0, 0, 0, 0, 0, 0, 0, 0, 0, 0, 0, 0, 0, 0, 0, 0, 0, 0, 0, 0, 0, 0, 0, 0, 0, 0, 0, 0, 0, 0, 0, 0, 98.279, 53.562, 0.737576, 118.425, 59.3923, 0.762404, 79.4957, 59.4279, 0.773234, 129.005, 62.9814, 0.34908, 0, 0, 0, 0, 0, 0, 0, 0, 0, 0, 0, 0, 0, 0, 0, 0, 0, 0], "face_keypoints_2d": [], "hand_left_keypoints_2d": [0, 0, 0, 0, 0, 0, 0, 0, 0, 0, 0, 0, 0, 0, 0, 0, 0, 0, 0, 0, 0, 0, 0, 0, 0, 0, 0, 0, 0, 0, 0, 0, 0, 0, 0, 0, 0, 0, 0, 0, 0, 0, 0, 0, 0, 0, 0, 0, 0, 0, 0, 0, 0, 0, 0, 0, 0, 0, 0, 0, 0, 0, 0], "hand_right_keypoints_2d": [0, 0, 0, 0, 0, 0, 0, 0, 0, 0, 0, 0, 0, 0, 0, 0, 0, 0, 0, 0, 0, 0, 0, 0, 0, 0, 0, 0, 0, 0, 0, 0, 0, 0, 0, 0, 0, 0, 0, 0, 0, 0, 0, 0, 0, 0, 0, 0, 0, 0, 0, 0, 0, 0, 0, 0, 0, 0, 0, 0, 0, 0, 0], "pose_keypoints_3d": [], "face_keypoints_3d": [], "hand_left_keypoints_3d": [], "hand_right_keypoints_3d": []}], "00022": [{"person_id": [-1], "pose_keypoints_2d": [107.788, 65.3399, 0.766192, 98.3122, 98.2815, 0.228477, 50.013, 95.9619, 0.309989, 0, 0, 0, 0, 0, 0, 0, 0, 0, 0, 0, 0, 0, 0, 0, 0, 0, 0, 0, 0, 0, 0, 0, 0, 0, 0, 0, 0, 0, 0, 0, 0, 0, 0, 0, 0, 98.2715, 53.5388, 0.764823, 118.413, 58.2694, 0.769332, 79.5051, 59.4072, 0.7698, 129.003, 62.987, 0.400145, 0, 0, 0, 0, 0, 0, 0, 0, 0, 0, 0, 0, 0, 0, 0, 0, 0, 0], "face_keypoints_2d": [], "hand_left_keypoints_2d": [0, 0, 0, 0, 0, 0, 0, 0, 0, 0, 0, 0, 0, 0, 0, 0, 0, 0, 0, 0, 0, 0, 0, 0, 0, 0, 0, 0, 0, 0, 0, 0, 0, 0, 0, 0, 0, 0, 0, 0, 0, 0, 0, 0, 0, 0, 0, 0, 0, 0, 0, 0, 0, 0, 0, 0, 0, 0, 0, 0, 0, 0, 0], "hand_right_keypoints_2d": [0, 0, 0, 0, 0, 0, 0, 0, 0, 0, 0, 0, 0, 0, 0, 0, 0, 0, 0, 0, 0, 0, 0, 0, 0, 0, 0, 0, 0, 0, 0, 0, 0, 0, 0, 0, 0, 0, 0, 0, 0, 0, 0, 0, 0, 0, 0, 0, 0, 0, 0, 0, 0, 0, 0, 0, 0, 0, 0, 0, 0, 0, 0], "pose_keypoints_3d": [], "face_keypoints_3d": [], "hand_left_keypoints_3d": [], "hand_right_keypoints_3d": []}], "00023": [{"person_id": [-1], "pose_keypoints_2d": [107.794, 66.5028, 0.724895, 98.318, 98.2916, 0.335824, 51.1551, 95.9678, 0.397058, 0, 0, 0, 0, 0, 0, 0, 0, 0, 0, 0, 0, 0, 0, 0, 0, 0, 0, 0, 0, 0, 0, 0, 0, 0, 0, 0, 0, 0, 0, 0, 0, 0, 0, 0, 0, 98.2594, 53.5332, 0.711311, 118.431, 58.2656, 0.725662, 79.4961, 59.4335, 0.751156, 129.005, 62.9436, 0.334749, 0, 0, 0, 0, 0, 0, 0, 0, 0, 0, 0, 0, 0, 0, 0, 0, 0, 0], "face_keypoints_2d": [], "hand_left_keypoints_2d": [0, 0, 0, 0, 0, 0, 0, 0, 0, 0, 0, 0, 0, 0, 0, 0, 0, 0, 0, 0, 0, 0, 0, 0, 0, 0, 0, 0, 0, 0, 0, 0, 0, 0, 0, 0, 0, 0, 0, 0, 0, 0, 0, 0, 0, 0, 0, 0, 0, 0, 0, 0, 0, 0, 0, 0, 0, 0, 0, 0, 0, 0, 0], "hand_right_keypoints_2d": [0, 0, 0, 0, 0, 0, 0, 0, 0, 0, 0, 0, 0, 0, 0, 0, 0, 0, 0, 0, 0, 0, 0, 0, 0, 0, 0, 0, 0, 0, 0, 0, 0, 0, 0, 0, 0, 0, 0, 0, 0, 0, 0, 0, 0, 0, 0, 0, 0, 0, 0, 0, 0, 0, 0, 0, 0, 0, 0, 0, 0, 0, 0], "pose_keypoints_3d": [], "face_keypoints_3d": [], "hand_left_keypoints_3d": [], "hand_right_keypoints_3d": []}], "00024": [{"person_id": [-1], "pose_keypoints_2d": [107.784, 65.3137, 0.776913, 98.2847, 97.1435, 0.257484, 51.1454, 94.7832, 0.342711, 0, 0, 0, 0, 0, 0, 0, 0, 0, 0, 0, 0, 0, 0, 0, 0, 0, 0, 0, 0, 0, 0, 0, 0, 0, 0, 0, 0, 0, 0, 0, 0, 0, 0, 0, 0, 98.2717, 52.4204, 0.773378, 118.404, 58.2495, 0.771643, 79.4997, 59.4086, 0.76646, 129.003, 62.9582, 0.367471, 0, 0, 0, 0, 0, 0, 0, 0, 0, 0, 0, 0, 0, 0, 0, 0, 0, 0], "face_keypoints_2d": [], "hand_left_keypoints_2d": [0, 0, 0, 0, 0, 0, 0, 0, 0, 0, 0, 0, 0, 0, 0, 0, 0, 0, 0, 0, 0, 0, 0, 0, 0, 0, 0, 0, 0, 0, 0, 0, 0, 0, 0, 0, 0, 0, 0, 0, 0, 0, 0, 0, 0, 0, 0, 0, 0, 0, 0, 0, 0, 0, 0, 0, 0, 0, 0, 0, 0, 0, 0], "hand_right_keypoints_2d": [0, 0, 0, 0, 0, 0, 0, 0, 0, 0, 0, 0, 0, 0, 0, 0, 0, 0, 0, 0, 0, 0, 0, 0, 0, 0, 0, 0, 0, 0, 0, 0, 0, 0, 0, 0, 0, 0, 0, 0, 0, 0, 0, 0, 0, 0, 0, 0, 0, 0, 0, 0, 0, 0, 0, 0, 0, 0, 0, 0, 0, 0, 0], "pose_keypoints_3d": [], "face_keypoints_3d": [], "hand_left_keypoints_3d": [], "hand_right_keypoints_3d": []}], "00025": [{"person_id": [-1], "pose_keypoints_2d": [107.742, 64.1563, 0.737506, 97.1382, 98.2959, 0.234453, 50.0059, 95.9529, 0.309119, 0, 0, 0, 0, 0, 0, 129.006, 108.945, 0.0553008, 0, 0, 0, 0, 0, 0, 0, 0, 0, 0, 0, 0, 0, 0, 0, 0, 0, 0, 0, 0, 0, 0, 0, 0, 0, 0, 0, 97.1522, 52.4104, 0.729489, 118.369, 57.0818, 0.745178, 79.469, 59.4276, 0.724533, 129, 61.8347, 0.425344, 0, 0, 0, 0, 0, 0, 0, 0, 0, 0, 0, 0, 0, 0, 0, 0, 0, 0], "face_keypoints_2d": [], "hand_left_keypoints_2d": [0, 0, 0, 0, 0, 0, 0, 0, 0, 0, 0, 0, 0, 0, 0, 0, 0, 0, 0, 0, 0, 0, 0, 0, 0, 0, 0, 0, 0, 0, 0, 0, 0, 0, 0, 0, 0, 0, 0, 0, 0, 0, 0, 0, 0, 0, 0, 0, 0, 0, 0, 0, 0, 0, 0, 0, 0, 0, 0, 0, 0, 0, 0], "hand_right_keypoints_2d": [0, 0, 0, 0, 0, 0, 0, 0, 0, 0, 0, 0, 0, 0, 0, 0, 0, 0, 0, 0, 0, 0, 0, 0, 0, 0, 0, 0, 0, 0, 0, 0, 0, 0, 0, 0, 0, 0, 0, 0, 0, 0, 0, 0, 0, 0, 0, 0, 0, 0, 0, 0, 0, 0, 0, 0, 0, 0, 0, 0, 0, 0, 0], "pose_keypoints_3d": [], "face_keypoints_3d": [], "hand_left_keypoints_3d": [], "hand_right_keypoints_3d": []}], "00026": [{"person_id": [-1], "pose_keypoints_2d": [107.732, 62.9916, 0.812858, 95.9639, 97.1624, 0.164984, 51.1624, 92.4507, 0.235573, 0, 0, 0, 0, 0, 0, 129.005, 107.744, 0.0709581, 0, 0, 0, 0, 0, 0, 0, 0, 0, 0, 0, 0, 0, 0, 0, 0, 0, 0, 0, 0, 0, 0, 0, 0, 0, 0, 0, 97.1358, 52.4004, 0.798787, 118.338, 57.0466, 0.799015, 79.4651, 59.4072, 0.7293, 128.998, 61.8257, 0.393897, 0, 0, 0, 0, 0, 0, 0, 0, 0, 0, 0, 0, 0, 0, 0, 0, 0, 0], "face_keypoints_2d": [], "hand_left_keypoints_2d": [0, 0, 0, 0, 0, 0, 0, 0, 0, 0, 0, 0, 0, 0, 0, 0, 0, 0, 0, 0, 0, 0, 0, 0, 0, 0, 0, 0, 0, 0, 0, 0, 0, 0, 0, 0, 0, 0, 0, 0, 0, 0, 0, 0, 0, 0, 0, 0, 0, 0, 0, 0, 0, 0, 0, 0, 0, 0, 0, 0, 0, 0, 0], "hand_right_keypoints_2d": [0, 0, 0, 0, 0, 0, 0, 0, 0, 0, 0, 0, 0, 0, 0, 0, 0, 0, 0, 0, 0, 0, 0, 0, 0, 0, 0, 0, 0, 0, 0, 0, 0, 0, 0, 0, 0, 0, 0, 0, 0, 0, 0, 0, 0, 0, 0, 0, 0, 0, 0, 0, 0, 0, 0, 0, 0, 0, 0, 0, 0, 0, 0], "pose_keypoints_3d": [], "face_keypoints_3d": [], "hand_left_keypoints_3d": [], "hand_right_keypoints_3d": []}], "00027": [{"person_id": [-1], "pose_keypoints_2d": [107.712, 62.9768, 0.837155, 97.1136, 97.1596, 0.162008, 51.1483, 92.4257, 0.192438, 0, 0, 0, 0, 0, 0, 0, 0, 0, 0, 0, 0, 0, 0, 0, 0, 0, 0, 0, 0, 0, 0, 0, 0, 0, 0, 0, 0, 0, 0, 0, 0, 0, 0, 0, 0, 97.1103, 52.3881, 0.835974, 118.321, 55.8865, 0.831467, 79.4422, 58.2476, 0.741132, 128.996, 61.7999, 0.409184, 0, 0, 0, 0, 0, 0, 0, 0, 0, 0, 0, 0, 0, 0, 0, 0, 0, 0], "face_keypoints_2d": [], "hand_left_keypoints_2d": [0, 0, 0, 0, 0, 0, 0, 0, 0, 0, 0, 0, 0, 0, 0, 0, 0, 0, 0, 0, 0, 0, 0, 0, 0, 0, 0, 0, 0, 0, 0, 0, 0, 0, 0, 0, 0, 0, 0, 0, 0, 0, 0, 0, 0, 0, 0, 0, 0, 0, 0, 0, 0, 0, 0, 0, 0, 0, 0, 0, 0, 0, 0], "hand_right_keypoints_2d": [0, 0, 0, 0, 0, 0, 0, 0, 0, 0, 0, 0, 0, 0, 0, 0, 0, 0, 0, 0, 0, 0, 0, 0, 0, 0, 0, 0, 0, 0, 0, 0, 0, 0, 0, 0, 0, 0, 0, 0, 0, 0, 0, 0, 0, 0, 0, 0, 0, 0, 0, 0, 0, 0, 0, 0, 0, 0, 0, 0, 0, 0, 0], "pose_keypoints_3d": [], "face_keypoints_3d": [], "hand_left_keypoints_3d": [], "hand_right_keypoints_3d": []}], "00028": [{"person_id": [-1], "pose_keypoints_2d": [107.693, 61.853, 0.856669, 94.7745, 98.2672, 0.176057, 49.9703, 93.5995, 0.208309, 0, 0, 0, 0, 0, 0, 129.005, 105.395, 0.0714362, 0, 0, 0, 0, 0, 0, 0, 0, 0, 0, 0, 0, 0, 0, 0, 0, 0, 0, 0, 0, 0, 0, 0, 0, 0, 0, 0, 95.9589, 52.3609, 0.851636, 118.299, 54.7288, 0.849932, 79.4096, 59.3993, 0.736174, 128.996, 61.7849, 0.368145, 0, 0, 0, 0, 0, 0, 0, 0, 0, 0, 0, 0, 0, 0, 0, 0, 0, 0], "face_keypoints_2d": [], "hand_left_keypoints_2d": [0, 0, 0, 0, 0, 0, 0, 0, 0, 0, 0, 0, 0, 0, 0, 0, 0, 0, 0, 0, 0, 0, 0, 0, 0, 0, 0, 0, 0, 0, 0, 0, 0, 0, 0, 0, 0, 0, 0, 0, 0, 0, 0, 0, 0, 0, 0, 0, 0, 0, 0, 0, 0, 0, 0, 0, 0, 0, 0, 0, 0, 0, 0], "hand_right_keypoints_2d": [0, 0, 0, 0, 0, 0, 0, 0, 0, 0, 0, 0, 0, 0, 0, 0, 0, 0, 0, 0, 0, 0, 0, 0, 0, 0, 0, 0, 0, 0, 0, 0, 0, 0, 0, 0, 0, 0, 0, 0, 0, 0, 0, 0, 0, 0, 0, 0, 0, 0, 0, 0, 0, 0, 0, 0, 0, 0, 0, 0, 0, 0, 0], "pose_keypoints_3d": [], "face_keypoints_3d": [], "hand_left_keypoints_3d": [], "hand_right_keypoints_3d": []}], "00029": [{"person_id": [-1], "pose_keypoints_2d": [105.408, 61.8425, 0.821074, 95.9569, 98.2836, 0.333539, 46.4787, 93.6281, 0.414568, 0, 0, 0, 0, 0, 0, 129.006, 107.722, 0.0597646, 0, 0, 0, 0, 0, 0, 0, 0, 0, 0, 0, 0, 0, 0, 0, 0, 0, 0, 0, 0, 0, 0, 0, 0, 0, 0, 0, 93.6234, 52.3325, 0.830902, 117.182, 54.6953, 0.852273, 79.3992, 58.2326, 0.731894, 128.994, 61.763, 0.462826, 0, 0, 0, 0, 0, 0, 0, 0, 0, 0, 0, 0, 0, 0, 0, 0, 0, 0], "face_keypoints_2d": [], "hand_left_keypoints_2d": [0, 0, 0, 0, 0, 0, 0, 0, 0, 0, 0, 0, 0, 0, 0, 0, 0, 0, 0, 0, 0, 0, 0, 0, 0, 0, 0, 0, 0, 0, 0, 0, 0, 0, 0, 0, 0, 0, 0, 0, 0, 0, 0, 0, 0, 0, 0, 0, 0, 0, 0, 0, 0, 0, 0, 0, 0, 0, 0, 0, 0, 0, 0], "hand_right_keypoints_2d": [0, 0, 0, 0, 0, 0, 0, 0, 0, 0, 0, 0, 0, 0, 0, 0, 0, 0, 0, 0, 0, 0, 0, 0, 0, 0, 0, 0, 0, 0, 0, 0, 0, 0, 0, 0, 0, 0, 0, 0, 0, 0, 0, 0, 0, 0, 0, 0, 0, 0, 0, 0, 0, 0, 0, 0, 0, 0, 0, 0, 0, 0, 0], "pose_keypoints_3d": [], "face_keypoints_3d": [], "hand_left_keypoints_3d": [], "hand_right_keypoints_3d": []}], "00030": [{"person_id": [-1], "pose_keypoints_2d": [105.404, 61.8361, 0.858702, 97.1136, 98.2711, 0.588562, 49.9697, 92.4537, 0.603808, 0, 0, 0, 0, 0, 0, 129.008, 103.027, 0.0806241, 0, 0, 0, 0, 0, 0, 0, 0, 0, 0, 0, 0, 0, 0, 0, 0, 0, 0, 0, 0, 0, 0, 0, 0, 0, 0, 0, 93.6314, 52.3404, 0.869919, 117.161, 54.6928, 0.875471, 79.405, 58.225, 0.805222, 128.993, 60.6515, 0.49513, 0, 0, 0, 0, 0, 0, 0, 0, 0, 0, 0, 0, 0, 0, 0, 0, 0, 0], "face_keypoints_2d": [], "hand_left_keypoints_2d": [0, 0, 0, 0, 0, 0, 0, 0, 0, 0, 0, 0, 0, 0, 0, 0, 0, 0, 0, 0, 0, 0, 0, 0, 0, 0, 0, 0, 0, 0, 0, 0, 0, 0, 0, 0, 0, 0, 0, 0, 0, 0, 0, 0, 0, 0, 0, 0, 0, 0, 0, 0, 0, 0, 0, 0, 0, 0, 0, 0, 0, 0, 0], "hand_right_keypoints_2d": [0, 0, 0, 0, 0, 0, 0, 0, 0, 0, 0, 0, 0, 0, 0, 0, 0, 0, 0, 0, 0, 0, 0, 0, 0, 0, 0, 0, 0, 0, 0, 0, 0, 0, 0, 0, 0, 0, 0, 0, 0, 0, 0, 0, 0, 0, 0, 0, 0, 0, 0, 0, 0, 0, 0, 0, 0, 0, 0, 0, 0, 0, 0], "pose_keypoints_3d": [], "face_keypoints_3d": [], "hand_left_keypoints_3d": [], "hand_right_keypoints_3d": []}], "00031": [{"person_id": [-1], "pose_keypoints_2d": [104.231, 62.9518, 0.802666, 97.1161, 97.1283, 0.22851, 46.4824, 94.7754, 0.213362, 0, 0, 0, 0, 0, 0, 129.006, 99.5135, 0.0507893, 0, 0, 0, 0, 0, 0, 0, 0, 0, 0, 0, 0, 0, 0, 0, 0, 0, 0, 0, 0, 0, 0, 0, 0, 0, 0, 0, 92.4469, 52.3674, 0.828546, 117.108, 54.6964, 0.830278, 78.2972, 58.2185, 0.710044, 128.989, 60.5831, 0.483329, 0, 0, 0, 0, 0, 0, 0, 0, 0, 0, 0, 0, 0, 0, 0, 0, 0, 0], "face_keypoints_2d": [], "hand_left_keypoints_2d": [0, 0, 0, 0, 0, 0, 0, 0, 0, 0, 0, 0, 0, 0, 0, 0, 0, 0, 0, 0, 0, 0, 0, 0, 0, 0, 0, 0, 0, 0, 0, 0, 0, 0, 0, 0, 0, 0, 0, 0, 0, 0, 0, 0, 0, 0, 0, 0, 0, 0, 0, 0, 0, 0, 0, 0, 0, 0, 0, 0, 0, 0, 0], "hand_right_keypoints_2d": [0, 0, 0, 0, 0, 0, 0, 0, 0, 0, 0, 0, 0, 0, 0, 0, 0, 0, 0, 0, 0, 0, 0, 0, 0, 0, 0, 0, 0, 0, 0, 0, 0, 0, 0, 0, 0, 0, 0, 0, 0, 0, 0, 0, 0, 0, 0, 0, 0, 0, 0, 0, 0, 0, 0, 0, 0, 0, 0, 0, 0, 0, 0], "pose_keypoints_3d": [], "face_keypoints_3d": [], "hand_left_keypoints_3d": [], "hand_right_keypoints_3d": []}], "00032": [{"person_id": [-1], "pose_keypoints_2d": [103.016, 63.0004, 0.795464, 94.7951, 97.1389, 0.245584, 45.3098, 93.6133, 0.225655, 0, 0, 0, 0, 0, 0, 129.007, 99.475, 0.0788443, 0, 0, 0, 0, 0, 0, 0, 0, 0, 0, 0, 0, 0, 0, 0, 0, 0, 0, 0, 0, 0, 0, 0, 0, 0, 0, 0, 91.2406, 52.4219, 0.827865, 115.966, 54.7411, 0.789758, 77.0897, 59.421, 0.676525, 128.988, 60.5806, 0.54631, 0, 0, 0, 0, 0, 0, 0, 0, 0, 0, 0, 0, 0, 0, 0, 0, 0, 0], "face_keypoints_2d": [], "hand_left_keypoints_2d": [0, 0, 0, 0, 0, 0, 0, 0, 0, 0, 0, 0, 0, 0, 0, 0, 0, 0, 0, 0, 0, 0, 0, 0, 0, 0, 0, 0, 0, 0, 0, 0, 0, 0, 0, 0, 0, 0, 0, 0, 0, 0, 0, 0, 0, 0, 0, 0, 0, 0, 0, 0, 0, 0, 0, 0, 0, 0, 0, 0, 0, 0, 0], "hand_right_keypoints_2d": [0, 0, 0, 0, 0, 0, 0, 0, 0, 0, 0, 0, 0, 0, 0, 0, 0, 0, 0, 0, 0, 0, 0, 0, 0, 0, 0, 0, 0, 0, 0, 0, 0, 0, 0, 0, 0, 0, 0, 0, 0, 0, 0, 0, 0, 0, 0, 0, 0, 0, 0, 0, 0, 0, 0, 0, 0, 0, 0, 0, 0, 0, 0], "pose_keypoints_3d": [], "face_keypoints_3d": [], "hand_left_keypoints_3d": [], "hand_right_keypoints_3d": []}], "00033": [{"person_id": [-1], "pose_keypoints_2d": [100.661, 62.9981, 0.738651, 90.0955, 97.1542, 0.244936, 40.5797, 95.9499, 0.243071, 0, 0, 0, 0, 0, 0, 129.007, 94.798, 0.128213, 0, 0, 0, 0, 0, 0, 0, 0, 0, 0, 0, 0, 0, 0, 0, 0, 0, 0, 0, 0, 0, 0, 0, 0, 0, 0, 0, 90.0302, 52.3859, 0.718185, 113.627, 53.5721, 0.701757, 73.5679, 58.2626, 0.538326, 128.977, 60.6238, 0.448933, 0, 0, 0, 0, 0, 0, 0, 0, 0, 0, 0, 0, 0, 0, 0, 0, 0, 0], "face_keypoints_2d": [], "hand_left_keypoints_2d": [0, 0, 0, 0, 0, 0, 0, 0, 0, 0, 0, 0, 0, 0, 0, 0, 0, 0, 0, 0, 0, 0, 0, 0, 0, 0, 0, 0, 0, 0, 0, 0, 0, 0, 0, 0, 0, 0, 0, 0, 0, 0, 0, 0, 0, 0, 0, 0, 0, 0, 0, 0, 0, 0, 0, 0, 0, 0, 0, 0, 0, 0, 0], "hand_right_keypoints_2d": [0, 0, 0, 0, 0, 0, 0, 0, 0, 0, 0, 0, 0, 0, 0, 0, 0, 0, 0, 0, 0, 0, 0, 0, 0, 0, 0, 0, 0, 0, 0, 0, 0, 0, 0, 0, 0, 0, 0, 0, 0, 0, 0, 0, 0, 0, 0, 0, 0, 0, 0, 0, 0, 0, 0, 0, 0, 0, 0, 0, 0, 0, 0], "pose_keypoints_3d": [], "face_keypoints_3d": [], "hand_left_keypoints_3d": [], "hand_right_keypoints_3d": []}], "00034": [{"person_id": [-1], "pose_keypoints_2d": [99.4809, 62.9899, 0.849222, 90.105, 97.1044, 0.296422, 41.7406, 95.9644, 0.281248, 0, 0, 0, 0, 0, 0, 129.007, 92.4318, 0.148387, 0, 0, 0, 0, 0, 0, 0, 0, 0, 0, 0, 0, 0, 0, 0, 0, 0, 0, 0, 0, 0, 0, 0, 0, 0, 0, 0, 88.8731, 52.402, 0.822043, 110.096, 53.5683, 0.795151, 72.4074, 58.2636, 0.680291, 120.733, 60.5652, 0.442341, 0, 0, 0, 0, 0, 0, 0, 0, 0, 0, 0, 0, 0, 0, 0, 0, 0, 0], "face_keypoints_2d": [], "hand_left_keypoints_2d": [0, 0, 0, 0, 0, 0, 0, 0, 0, 0, 0, 0, 0, 0, 0, 0, 0, 0, 0, 0, 0, 0, 0, 0, 0, 0, 0, 0, 0, 0, 0, 0, 0, 0, 0, 0, 0, 0, 0, 0, 0, 0, 0, 0, 0, 0, 0, 0, 0, 0, 0, 0, 0, 0, 0, 0, 0, 0, 0, 0, 0, 0, 0], "hand_right_keypoints_2d": [0, 0, 0, 0, 0, 0, 0, 0, 0, 0, 0, 0, 0, 0, 0, 0, 0, 0, 0, 0, 0, 0, 0, 0, 0, 0, 0, 0, 0, 0, 0, 0, 0, 0, 0, 0, 0, 0, 0, 0, 0, 0, 0, 0, 0, 0, 0, 0, 0, 0, 0, 0, 0, 0, 0, 0, 0, 0, 0, 0, 0, 0, 0], "pose_keypoints_3d": [], "face_keypoints_3d": [], "hand_left_keypoints_3d": [], "hand_right_keypoints_3d": []}], "00035": [{"person_id": [-1], "pose_keypoints_2d": [97.1392, 61.8576, 0.667052, 88.9182, 95.9701, 0.205657, 40.5789, 97.1251, 0.224855, 0, 0, 0, 0, 0, 0, 129.006, 92.4386, 0.202154, 0, 0, 0, 0, 0, 0, 0, 0, 0, 0, 0, 0, 0, 0, 0, 0, 0, 0, 0, 0, 0, 0, 0, 0, 0, 0, 0, 84.1636, 52.3802, 0.64692, 107.757, 52.3946, 0.653048, 70.0907, 60.5432, 0.604197, 118.33, 60.5377, 0.320803, 0, 0, 0, 0, 0, 0, 0, 0, 0, 0, 0, 0, 0, 0, 0, 0, 0, 0], "face_keypoints_2d": [], "hand_left_keypoints_2d": [0, 0, 0, 0, 0, 0, 0, 0, 0, 0, 0, 0, 0, 0, 0, 0, 0, 0, 0, 0, 0, 0, 0, 0, 0, 0, 0, 0, 0, 0, 0, 0, 0, 0, 0, 0, 0, 0, 0, 0, 0, 0, 0, 0, 0, 0, 0, 0, 0, 0, 0, 0, 0, 0, 0, 0, 0, 0, 0, 0, 0, 0, 0], "hand_right_keypoints_2d": [0, 0, 0, 0, 0, 0, 0, 0, 0, 0, 0, 0, 0, 0, 0, 0, 0, 0, 0, 0, 0, 0, 0, 0, 0, 0, 0, 0, 0, 0, 0, 0, 0, 0, 0, 0, 0, 0, 0, 0, 0, 0, 0, 0, 0, 0, 0, 0, 0, 0, 0, 0, 0, 0, 0, 0, 0, 0, 0, 0, 0, 0, 0], "pose_keypoints_3d": [], "face_keypoints_3d": [], "hand_left_keypoints_3d": [], "hand_right_keypoints_3d": []}], "00036": [{"person_id": [-1], "pose_keypoints_2d": [94.7744, 62.9688, 0.753462, 88.8941, 97.1067, 0.211108, 41.7544, 97.1063, 0.220119, 0, 0, 0, 0, 0, 0, 128.999, 93.6177, 0.281093, 0, 0, 0, 0, 0, 0, 0, 0, 0, 0, 0, 0, 0, 0, 0, 0, 0, 0, 0, 0, 0, 0, 0, 0, 0, 0, 0, 81.8509, 52.4102, 0.797722, 105.401, 52.4242, 0.759101, 70.0193, 59.3874, 0.684597, 117.17, 58.2262, 0.582968, 0, 0, 0, 0, 0, 0, 0, 0, 0, 0, 0, 0, 0, 0, 0, 0, 0, 0], "face_keypoints_2d": [], "hand_left_keypoints_2d": [0, 0, 0, 0, 0, 0, 0, 0, 0, 0, 0, 0, 0, 0, 0, 0, 0, 0, 0, 0, 0, 0, 0, 0, 0, 0, 0, 0, 0, 0, 0, 0, 0, 0, 0, 0, 0, 0, 0, 0, 0, 0, 0, 0, 0, 0, 0, 0, 0, 0, 0, 0, 0, 0, 0, 0, 0, 0, 0, 0, 0, 0, 0], "hand_right_keypoints_2d": [0, 0, 0, 0, 0, 0, 0, 0, 0, 0, 0, 0, 0, 0, 0, 0, 0, 0, 0, 0, 0, 0, 0, 0, 0, 0, 0, 0, 0, 0, 0, 0, 0, 0, 0, 0, 0, 0, 0, 0, 0, 0, 0, 0, 0, 0, 0, 0, 0, 0, 0, 0, 0, 0, 0, 0, 0, 0, 0, 0, 0, 0, 0], "pose_keypoints_3d": [], "face_keypoints_3d": [], "hand_left_keypoints_3d": [], "hand_right_keypoints_3d": []}], "00037": [{"person_id": [-1], "pose_keypoints_2d": [91.2533, 61.8297, 0.781694, 87.7077, 95.9511, 0.282055, 38.2009, 97.1633, 0.259324, 0, 0, 0, 0, 0, 0, 128.998, 93.6201, 0.385075, 0, 0, 0, 0, 0, 0, 0, 0, 0, 0, 0, 0, 0, 0, 0, 0, 0, 0, 0, 0, 0, 0, 0, 0, 0, 0, 0, 79.5097, 52.3796, 0.803999, 101.859, 52.3473, 0.753831, 66.4778, 59.4426, 0.605712, 114.817, 58.2225, 0.526366, 0, 0, 0, 0, 0, 0, 0, 0, 0, 0, 0, 0, 0, 0, 0, 0, 0, 0], "face_keypoints_2d": [], "hand_left_keypoints_2d": [0, 0, 0, 0, 0, 0, 0, 0, 0, 0, 0, 0, 0, 0, 0, 0, 0, 0, 0, 0, 0, 0, 0, 0, 0, 0, 0, 0, 0, 0, 0, 0, 0, 0, 0, 0, 0, 0, 0, 0, 0, 0, 0, 0, 0, 0, 0, 0, 0, 0, 0, 0, 0, 0, 0, 0, 0, 0, 0, 0, 0, 0, 0], "hand_right_keypoints_2d": [0, 0, 0, 0, 0, 0, 0, 0, 0, 0, 0, 0, 0, 0, 0, 0, 0, 0, 0, 0, 0, 0, 0, 0, 0, 0, 0, 0, 0, 0, 0, 0, 0, 0, 0, 0, 0, 0, 0, 0, 0, 0, 0, 0, 0, 0, 0, 0, 0, 0, 0, 0, 0, 0, 0, 0, 0, 0, 0, 0, 0, 0, 0], "pose_keypoints_3d": [], "face_keypoints_3d": [], "hand_left_keypoints_3d": [], "hand_right_keypoints_3d": []}], "00038": [{"person_id": [-1], "pose_keypoints_2d": [90.0153, 62.9759, 0.825569, 87.7203, 97.1457, 0.318882, 39.4066, 97.1195, 0.270857, 0, 0, 0, 0, 0, 0, 128.999, 98.2881, 0.407345, 0, 0, 0, 0, 0, 0, 0, 0, 0, 0, 0, 0, 0, 0, 0, 0, 0, 0, 0, 0, 0, 0, 0, 0, 0, 0, 0, 79.4116, 53.5172, 0.819178, 99.4812, 53.5211, 0.827594, 63.0143, 60.5594, 0.697755, 111.277, 59.4253, 0.660965, 0, 0, 0, 0, 0, 0, 0, 0, 0, 0, 0, 0, 0, 0, 0, 0, 0, 0], "face_keypoints_2d": [], "hand_left_keypoints_2d": [0, 0, 0, 0, 0, 0, 0, 0, 0, 0, 0, 0, 0, 0, 0, 0, 0, 0, 0, 0, 0, 0, 0, 0, 0, 0, 0, 0, 0, 0, 0, 0, 0, 0, 0, 0, 0, 0, 0, 0, 0, 0, 0, 0, 0, 0, 0, 0, 0, 0, 0, 0, 0, 0, 0, 0, 0, 0, 0, 0, 0, 0, 0], "hand_right_keypoints_2d": [0, 0, 0, 0, 0, 0, 0, 0, 0, 0, 0, 0, 0, 0, 0, 0, 0, 0, 0, 0, 0, 0, 0, 0, 0, 0, 0, 0, 0, 0, 0, 0, 0, 0, 0, 0, 0, 0, 0, 0, 0, 0, 0, 0, 0, 0, 0, 0, 0, 0, 0, 0, 0, 0, 0, 0, 0, 0, 0, 0, 0, 0, 0], "pose_keypoints_3d": [], "face_keypoints_3d": [], "hand_left_keypoints_3d": [], "hand_right_keypoints_3d": []}]}, "label": "Thumb Up,,,,,,,", "id": "3841"}